qarray_rust_core-1.3.1.dist-info/METADATA
qarray_rust_core-1.3.1.dist-info/WHEEL
qarray_rust_core-1.3.1.dist-info/license_files/LICENSE.md
qarray_rust_core/__init__.py
qarray_rust_core/qarray_rust_core.pypy310-pp73-x86-linux-gnu.so
qarray_rust_core-1.3.1.dist-info/RECORD
