Metadata-Version: 2.1
Name: qarray_rust_core
Version: 1.3.1
Classifier: Topic :: Scientific/Engineering :: Physics
Classifier: Operating System :: OS Independent
Classifier: Programming Language :: Rust
Classifier: Programming Language :: Python :: Implementation :: CPython
License-File: LICENSE.md
Author-email: Barnaby van Straaten <barnaby.vanstraaten@kellogg.ox.ac.uk>
Requires-Python: >=3.10
Project-URL: Homepage, https://github.com/b-vanstraaten/qarray-rust-core
